imagecorruptions/__init__.py
imagecorruptions/corruptions.py
imagecorruptions/frost/frost1.png
imagecorruptions/frost/frost2.png
imagecorruptions/frost/frost3.png
imagecorruptions/frost/frost4.jpg
imagecorruptions/frost/frost5.jpg
imagecorruptions/frost/frost6.jpg
imagecorruptions_imaug-1.1.3.dist-info/licenses/LICENSE
imagecorruptions_imaug-1.1.3.dist-info/licenses/NOTICE
imagecorruptions_imaug-1.1.3.dist-info/METADATA
imagecorruptions_imaug-1.1.3.dist-info/WHEEL
imagecorruptions_imaug-1.1.3.dist-info/top_level.txt
imagecorruptions_imaug-1.1.3.dist-info/RECORD
