Metadata-Version: 2.4
Name: imagecorruptions-imaug
Version: 1.1.3
Summary: This package provides a set of image corruptions.
Home-page: https://github.com/imaug/imagecorruptions
Author: imaug
Author-email: ej_foss@mailbox.org
Classifier: Programming Language :: Python :: 3
Classifier: License :: OSI Approved :: Apache Software License
Classifier: Operating System :: OS Independent
License-File: LICENSE
License-File: NOTICE
Requires-Dist: numpy>=1.16
Requires-Dist: Pillow>=5.4.1
Requires-Dist: scikit-image>=0.15
Requires-Dist: opencv-python>=3.4.5
Requires-Dist: scipy>=1.2.1
Requires-Dist: numba>=0.53.0
Requires-Dist: setuptools; python_version >= "3.12"
Dynamic: author
Dynamic: author-email
Dynamic: classifier
Dynamic: description
Dynamic: description-content-type
Dynamic: home-page
Dynamic: license-file
Dynamic: requires-dist
Dynamic: summary
